{"tZURE3V32Vpljf8QMp3uvw==":"gallery04-1200x800.jpg","ljTmfiDK+nDmGEt/XOGZbQ==":"gallery04-1-1200x800.jpg","K6uA8jeaexAYBmVCe6jlZQ==":"gallery04-2-1200x800.jpg","zB5FxZjNmH0sl1djk9oMVQ==":"gallery07-1200x800.jpg","o3QSqRy+DO6ofB+wqO6BfQ==":"gallery06-1200x800.jpg","ykt8diTXUZMyzz2nxmK2Xg==":"gallery04-3-1200x800.jpg","+JmH31rGTR/xoNgWFNlAzQ==":"gallery07-1-1200x800.jpg","RRpc00zL3gCmJ5LI5L7lkg==":"jakob-owens-102203-2000x1333.jpg","D07VKXtXX3B4HCjhrhxEPA==":"joshua-niedermayer-266955-2000x1334.jpg","ZBnwdPZO2m3QtuUAowbgmA==":"andrew-tanglao-505288-2000x1311.jpg","EtufoHcofvC98kgaaB1YwA==":"10-1200x800.jpg","ahiazdjMpLxyqxrKiT2PgA==":"joshua-niedermayer-266955-1920x1281.jpg","5NDW1FvCfh+ybnLlccpNdw==":"andrew-tanglao-505288-1920x1259.jpg","2MmoBtOI9/tmfN7Xwa8Omg==":"jakob-owens-102203-1920x1280.jpg","DtxgzHIm7NHZM8GwJiWTog==":"1-1920x1280.jpg","3w0DrjnVdnxG9kSdLrva2g==":"6a920fe9-fda9-4725-8ca3-f6d700a9c3b4-441x539.jpg","ZTpNb3wvvOD6wuke0CmMGQ==":"8fb3aeeb-8826-452b-9b4a-3741e53ce18b-960x1280.jpg","uGfUtdlnxEc8DamWBzvAdw==":"topo%20site%20-1920x1280.png","WOpK0x+TM/rFvQmjelrUqQ==":"topo%20site%20-1920x1280.png","tsVzdGpCr86yfX8gbq3Kqw==":"design%20sem%20nome-1920x1200.png","/QLVomDFGnFVmn3eiMSBQA==":"design%20sem%20nome%20(1)-1920x1150.png","nmIli9xOFFcehyxuiF/VRw==":"design%20sem%20nome%20(2)-1920x1100.png","mgVhCPSOdZKz1sQePKZy0g==":"3-800x1000.png","o6vK39gO+f65U6p6d7uz3A==":"5-800x1000.png","/CWF6VGURUQeVk+79Cy4GA==":"7-800x1000.png","TjSfIwtb42SiLm1rSErClA==":"1-1-800x1000.png","+recJuH2C4HYdA2o7X69Hg==":"4-1-800x1000.png","e1fb8epLaI/qxFPG22C7Kg==":"2-2-800x1000.png","BVvPtbrxEAmzujybdR9glg==":"social-media%20(1)-164x164.png","nSm39OqbmogGyZNzoqBMug==":"1-1044x696.png","2C6razNgpnhzZXeniA4fvQ==":"2-1044x696.png","3vu4IGyPsvVsZKRxo08IDg==":"design%20sem%20nome%20(4)-1920x1050.png","sKJCogD75LJB0pQ1AG+yww==":"design%20sem%20nome%20(5)-1920x1050.png","7bjXk05hvo66mgYG/75YWA==":"design%20sem%20nome%20(6)-1920x1050.png","iAMFLwew5G7bD9BVNWA0DA==":"design%20sem%20nome%20(7)-1920x1050.png","riLhJ/dz+VBv2HCP8d59MQ==":"design%20sem%20nome%20(8)-1920x1050.png","oNd4s+uoWGGjLs5RRU8G0w==":"design%20sem%20nome%20(9)-1920x1050.png","JxQkL6h2SfmSz0ZEy4HScQ==":"1-2-800x1000.png","WuFV4MgbUDwLwCYXCZhtBQ==":"2-3-800x1000.png","sEMAGQrGJiDBvaV4m2y4mw==":"5-1-800x1000.png","vYKcoexd+aTNPn5TnsUOnw==":"6-1-800x1000.png","wxqgyev/dMXulCOxP6Q+Ag==":"4-3-800x1000.png","U3a4ZKaJ4PQ0M2Fxws1j9g==":"7-1-800x1000.png","vp9roUG2tEb6TfLhbwzaFQ==":"af644c19-f1ac-47d5-9b97-468822ebe6f2-853x1280.jpg","mJ15qN3nP2qAFD/7IQr60Q==":"design%20sem%20nome%20(10)-1920x1050.png","/lfMzfWSZrzFQPJ8AJs31Q==":"design%20sem%20nome%20(11)-1920x1281.png","925BeKMpPk6uNMsVzMPDPA==":"design%20sem%20nome%20(12)-1920x1281.png","CEbSl78SRQXhRKt0JooM4w==":"design%20sem%20nome%20(12)-1920x1281.png","RYtzMfHVNdxYQKCakM7ymA==":"design%20sem%20nome%20(12)-1920x1281.png","tQqQef146mgRmLAz25PJJQ==":"3-2-800x1000.png","GNy5w7Wui4o+svlQRhGkrw==":"5-2-800x1000.png","dSyu17jRJtY8XTXoWAPWAQ==":"7-2-800x1000.png","R7CbyuHgivUn1WDTjwsqwQ==":"1-4-800x1000.png","jLmErTnuQTr+dQDEWpjdpQ==":"2-5-800x1000.png","sKFw9c1mJadr7byLcOqfRA==":"4-5-800x1000.png","+i2yRO3XscLqIaQf8orcDQ==":"6-3-800x1000.png","TY7BFrslPyt3jg9TAo5hXQ==":"f2527ebc-ab5f-4e27-a1c9-184a20014afd-853x1280.jpg","iZ6ICpiRTFKJPOn9Y90G4A==":"design%20sem%20nome%20(13)-1920x1281.png","7vxSwJMfQSqWL0U8PK7CTA==":"1-1-1044x696.png","1WFJO3o5BEZTaXtFMe04Gg==":"2-1-1044x696.png","mnOPrhZISYjv0qz8fI88SQ==":"5-3-800x1000.png","5+9OHLdbgC3iywvssiweCQ==":"6-4-800x1000.png","QZ+nAS5ZheFiF24rgySTgQ==":"3e90530a-d089-4ee7-9d55-273546bde8b5-853x1280.jpg","2rzZmX4fKgXT7K9i4J1Dog==":"1-6-800x1000.png","k6KkrUQXz5MwaurNMeAAKA==":"4-7-800x1000.png","zeBDyaP3IbFdPKUUVAX+Kw==":"7-4-800x1000.png","93YjjU5TsqALP82VxIX7Jg==":"2-8-800x1000.png","6XcEQiiYqT9q0ByTc2Lqyg==":"3-5-800x1000.png","o8TZEXRIhW7OR84BOFrnJg==":"f2527ebc-ab5f-4e27-a1c9-184a20014afd-853x1280.jpeg","zGjvWGRZRSuMyi0PDY4c9A==":"6691085e-9bd2-42cb-aa80-60ef581e4200-853x1280.jpg","qQwTqxlFcOuMlZIc00Vb7g==":"6691085e-9bd2-42cb-aa80-60ef581e4200-853x1280.jpeg","fArmWoP7cY96aMNkZ5ZAEA==":"8-800x1000.png","xkks2Nacb9SF8O77weVrHg==":"10-800x1000.png","IzJ+aOLkI5M6JO7rlQ7pIQ==":"11-800x1000.png","FG0rnNZdR0oXjNd1R8wTqA==":"13-800x1000.png","nx+lii0QK2MOdV/vTxMsyw==":"12-800x1000.png","tyGXKfFFHso1QoA8J4aU0Q==":"15-800x1000.png","yHBbiyEDQZ+YYIF8eSXIWQ==":"9-800x1000.png","Yd26DmRIsNnVR5WIy/VUDA==":"f2527ebc-ab5f-4e27-a1c9-184a20014afd-1-853x1280.jpeg","JZ1gARJ1d/112ECiPwzQ1w==":"sale-800x1000.png","kUWkNjtTl8mYpQFVlbEQzQ==":"5ea3e727-2164-4a1e-9240-8a6ceada5a15-853x1280.jpg","taHdvKBd5NDuYESqamsEaA==":"sale%20(1)-800x1000.png","TYFaVnK+g0QRmxtbF3BmWw==":"sale%20(2)-800x1000.png","x0+p2YD2vn8u8123zkFHsg==":"22-800x1000.png","amRVa+CNBZ7AgDiXyjW6hw==":"21-800x1000.png","kFQOi/qLVLShNd4KqvQ7mw==":"20-800x1000.png","Cbx+xCaDL9E885fMJIF7BA==":"18-800x1000.png","2Dejg17l2C/UvHxzh55qTw==":"19-800x1000.png"}